{
  "track_id": "t4H_Zoh7G5A",
  "language": "en-nP7-2PuUl7o",
  "name": "English - en",
  "source": "subtitles",
  "cues": [
    {
      "start": 4.633,
      "end": 7.0,
      "text": "♪ ♪"
    },
    {
      "start": 18.166,
      "end": 20.166,
      "text": "♪ ♪"
    },
    {
      "start": 30.4,
      "end": 31.566,
      "text": "♪ J-LO! ♪"
    },
    {
      "start": 34.466,
      "end": 38.266,
      "text": "♪ IT'S A NEW GENERATION ♪"
    },
    {
      "start": 39.266,
      "end": 41.333,
      "text": "♪ OF PARTY PEOPLE ♪"
    },
    {
      "start": 41.366,
      "end": 44.333,
      "text": "♪ DALE GET ON THE FLOOR DALE GET ON THE FLOOR ♪"
    },
    {
      "start": 44.366,
      "end": 50.066,
      "text": "♪ LET ME INTRODUCE YOU TO MY PARTY PEOPLE IN THE CLUB... ♪"
    },
    {
      "start": 51.366,
      "end": 52.533,
      "text": "♪ I'M LOOSE ♪"
    },
    {
      "start": 52.566,
      "end": 54.533,
      "text": "♪ AND EVERYBODY KNOWS I GET OFF THE TRAIN ♪"
    },
    {
      "start": 54.566,
      "end": 56.333000000000006,
      "text": "♪ BABY IT'S THE TRUTH ♪"
    },
    {
      "start": 56.366,
      "end": 58.133,
      "text": "♪ I'M LIKE INCEPTION I PLAY WITH YOUR BRAIN ♪"
    },
    {
      "start": 58.166,
      "end": 60.132999999999996,
      "text": "♪ SO I DON'T SLEEP OR SNOOZE ♪"
    },
    {
      "start": 60.166,
      "end": 63.532999999999994,
      "text": "♪ I DON'T PLAY NO GAMES SO DON'T GET IT CONFUSED, NO ♪"
    },
    {
      "start": 63.566,
      "end": 66.13300000000001,
      "text": "♪ CUZ YOU WILL LOSE, YEAH ♪"
    },
    {
      "start": 66.166,
      "end": 67.566,
      "text": "♪ NOW PUM-PU-PUM P-P-P-PUMP IT UP ♪"
    },
    {
      "start": 67.6,
      "end": 69.466,
      "text": "♪ AND BACK IT UP LIKE A TONKA TRUCK, DALE ♪"
    },
    {
      "start": 70.2,
      "end": 73.666,
      "text": "♪ IF YOU GO HARD YOU GOTTA GET ON THE FLOOR ♪"
    },
    {
      "start": 73.7,
      "end": 77.46600000000001,
      "text": "♪ IF YOU'RE A PARTY FREAK THEN STEP ON THE FLOOR ♪"
    },
    {
      "start": 77.5,
      "end": 80.3,
      "text": "♪ IF YOU'RE AN ANIMAL THEN TEAR UP THE FLOOR ♪"
    },
    {
      "start": 80.333,
      "end": 82.3,
      "text": "♪ BREAK A SWEAT ON THE FLOOR♪"
    },
    {
      "start": 82.333,
      "end": 85.066,
      "text": "♪ YEAH WE WORK ON THE FLOOR ♪"
    },
    {
      "start": 85.2,
      "end": 88.63300000000001,
      "text": "♪ DON'T STOP KEEP IT MOVING PUT YOUR DRINKS UP ♪"
    },
    {
      "start": 88.666,
      "end": 92.39999999999999,
      "text": "♪ PICK YOUR BODY UP AND DROP IT ON THE FLOOR ♪"
    },
    {
      "start": 92.433,
      "end": 96.13300000000001,
      "text": "♪ LET THE RHYTHM CHANGE YOUR WORLD ON THE FLOOR ♪"
    },
    {
      "start": 96.166,
      "end": 99.26599999999999,
      "text": "♪ YOU KNOW WE'RE RUNNING TONIGHT ON THE FLOOR ♪"
    },
    {
      "start": 99.3,
      "end": 102.7,
      "text": "♪ BRAZIL MOROCCO LONDON TO IBIZA ♪"
    },
    {
      "start": 102.733,
      "end": 106.566,
      "text": "♪ STRAIGHT TO LA, NEW YORK VEGAS TO AFRICA ♪"
    },
    {
      "start": 106.6,
      "end": 108.633,
      "text": "♪ DANCE THE NIGHT AWAY ♪"
    },
    {
      "start": 108.666,
      "end": 112.166,
      "text": "♪ LIVE YOUR LIFE, AND STAY YOUNG ON THE FLOOR ♪"
    },
    {
      "start": 114.3,
      "end": 116.166,
      "text": "♪ DANCE THE NIGHT AWAY ♪"
    },
    {
      "start": 116.2,
      "end": 119.46600000000001,
      "text": "♪ GRAB SOMEBODY DRINK A LITTLE MORE ♪"
    },
    {
      "start": 125.366,
      "end": 129.533,
      "text": "♪ LALALALALA LALALALALALA LALA LALA ♪"
    },
    {
      "start": 129.566,
      "end": 132.6,
      "text": "♪ TONIGHT WE GON' BE IT ON THE FLOOR ♪"
    },
    {
      "start": 132.633,
      "end": 137.166,
      "text": "♪ LALALALALALALALALALALALA LALA ♪"
    },
    {
      "start": 137.2,
      "end": 140.333,
      "text": "♪ TONIGHT WE GON' BE IT ON THE FLOOR ♪"
    },
    {
      "start": 140.366,
      "end": 144.133,
      "text": "♪ I KNOW YOU GOT IT CLAP YOUR HANDS ON THE FLOOR ♪"
    },
    {
      "start": 144.166,
      "end": 147.566,
      "text": "♪ AND KEEP ON ROCKIN', ROCK IT UP ON THE FLOOR ♪"
    },
    {
      "start": 147.6,
      "end": 150.466,
      "text": "♪ IF YOU'RE A CRIMINAL KILL IT ON THE FLOOR ♪"
    },
    {
      "start": 150.5,
      "end": 155.36599999999999,
      "text": "♪ STEAL IT QUICK ON THE FLOOR, ON THE FLOOR ♪"
    },
    {
      "start": 155.4,
      "end": 158.633,
      "text": "♪ DON'T STOP KEEP IT MOVING PUT YOUR DRINKS UP ♪"
    },
    {
      "start": 158.666,
      "end": 162.433,
      "text": "♪ ITS GETTING ILL IT'S GETTING SICK ON THE FLOOR ♪"
    },
    {
      "start": 162.466,
      "end": 166.3,
      "text": "♪ WE NEVER QUIT, WE NEVER REST ON THE FLOOR ♪"
    },
    {
      "start": 166.333,
      "end": 169.433,
      "text": "♪ IF I AIN'T WRONG WE'LL PROBABLY DIE ON THE FLOOR ♪"
    },
    {
      "start": 169.466,
      "end": 173.26600000000002,
      "text": "♪ BRAZIL MOROCCO LONDON TO IBIZA ♪"
    },
    {
      "start": 173.3,
      "end": 177.20000000000002,
      "text": "♪ STRAIGHT TO LA, NEW YORK VEGAS TO AFRICA ♪"
    },
    {
      "start": 177.233,
      "end": 178.733,
      "text": "♪ DANCE THE NIGHT AWAY ♪"
    },
    {
      "start": 178.766,
      "end": 182.266,
      "text": "♪ LIVE YOUR LIFE, AND STAY YOUNG ON THE FLOOR ♪"
    },
    {
      "start": 184.466,
      "end": 186.333,
      "text": "♪ DANCE THE NIGHT AWAY ♪"
    },
    {
      "start": 186.366,
      "end": 189.566,
      "text": "♪ GRAB SOMEBODY DRINK A LITTLE MORE ♪"
    },
    {
      "start": 195.566,
      "end": 199.666,
      "text": "♪ LALALALALALALALALALAL LALA LALA ♪"
    },
    {
      "start": 199.7,
      "end": 202.7,
      "text": "♪ TONIGHT WE GON' BE IT ON THE FLOOR ♪"
    },
    {
      "start": 202.733,
      "end": 207.333,
      "text": "♪ LALALALALALALALALALALALA LALA ♪"
    },
    {
      "start": 207.366,
      "end": 209.76600000000002,
      "text": "♪ TONIGHT WE GON' BE IT ON THE FLOOR ♪"
    },
    {
      "start": 210.0,
      "end": 211.6,
      "text": "♪ THAT BADONKA DONK IS LIKE A TRUNK FULL OF BASS ON AN ♪"
    },
    {
      "start": 211.633,
      "end": 213.666,
      "text": "♪ OLD SCHOOL CHEVY SEVEN TRE DONK A DONK ♪"
    },
    {
      "start": 213.7,
      "end": 215.5,
      "text": "♪ ALL I NEED IS SOME VODKA SOME SHONK A KONK ♪"
    },
    {
      "start": 215.533,
      "end": 217.29999999999998,
      "text": "♪ AND WATCH SHE GON' GET DONKEY KONGED ♪"
    },
    {
      "start": 217.333,
      "end": 219.0,
      "text": "♪ BABY IF YOU'RE READY FOR THINGS TO GET HEAVY ♪"
    },
    {
      "start": 219.033,
      "end": 221.56599999999997,
      "text": "♪ I GET ON THE FLOOR AND ACT A FOOL IF YOU LET ME, DALE ♪"
    },
    {
      "start": 221.6,
      "end": 223.13299999999998,
      "text": "♪ DON'T BELIEVE ME JUST BET ME ♪"
    },
    {
      "start": 223.166,
      "end": 225.4,
      "text": "♪ MY NAME AIN'T KEATH BUT I SEE THE WAY YOU SWEAT ME ♪"
    },
    {
      "start": 225.433,
      "end": 228.63299999999998,
      "text": "♪ L.A. MIAMI NEW YORK SAY NO MORE GET ON THE FLOOR ♪"
    },
    {
      "start": 228.666,
      "end": 233.266,
      "text": "♪ LALALALALALALALALALAL LALA LALA ♪"
    },
    {
      "start": 233.3,
      "end": 236.26600000000002,
      "text": "♪ TONIGHT WE GON' BE IT ON THE FLOOR ♪"
    },
    {
      "start": 236.3,
      "end": 240.566,
      "text": "♪ LALALALALALALALALALALALA LALA ♪"
    },
    {
      "start": 240.6,
      "end": 243.533,
      "text": "♪ TONIGHT WE GON' BE IT ON THE FLOOR ♪"
    },
    {
      "start": 243.566,
      "end": 248.0,
      "text": "♪ LALALALALALALALALALAL LALA LALA ♪"
    },
    {
      "start": 248.033,
      "end": 251.2,
      "text": "♪ TONIGHT WE GON' BE IT ON THE FLOOR ♪"
    },
    {
      "start": 252.733,
      "end": 256.733,
      "text": "♪ ♪"
    }
  ]
}